flappy_bird_gymnasium/__init__.py
flappy_bird_gymnasium/cli.py
flappy_bird_gymnasium/assets/audio/die.ogg
flappy_bird_gymnasium/assets/audio/die.wav
flappy_bird_gymnasium/assets/audio/hit.ogg
flappy_bird_gymnasium/assets/audio/hit.wav
flappy_bird_gymnasium/assets/audio/point.ogg
flappy_bird_gymnasium/assets/audio/point.wav
flappy_bird_gymnasium/assets/audio/swoosh.ogg
flappy_bird_gymnasium/assets/audio/swoosh.wav
flappy_bird_gymnasium/assets/audio/wing.ogg
flappy_bird_gymnasium/assets/audio/wing.wav
flappy_bird_gymnasium/assets/model/LIDAR_AVG_12steps.h5
flappy_bird_gymnasium/assets/model/LIDAR_AVG_16steps.h5
flappy_bird_gymnasium/assets/model/LIDAR_AVG_16steps_0px.h5
flappy_bird_gymnasium/assets/model/LIDAR_AVG_16steps_15px.h5
flappy_bird_gymnasium/assets/model/LIDAR_AVG_16steps_30px.h5
flappy_bird_gymnasium/assets/model/LIDAR_MAX_12steps.h5
flappy_bird_gymnasium/assets/model/LIDAR_MAX_16steps.h5
flappy_bird_gymnasium/assets/model/LIDAR_t-1_12steps.h5
flappy_bird_gymnasium/assets/model/LIDAR_t-1_16steps.h5
flappy_bird_gymnasium/assets/model/model.h5
flappy_bird_gymnasium/assets/sprites/0.png
flappy_bird_gymnasium/assets/sprites/1.png
flappy_bird_gymnasium/assets/sprites/2.png
flappy_bird_gymnasium/assets/sprites/3.png
flappy_bird_gymnasium/assets/sprites/4.png
flappy_bird_gymnasium/assets/sprites/5.png
flappy_bird_gymnasium/assets/sprites/6.png
flappy_bird_gymnasium/assets/sprites/7.png
flappy_bird_gymnasium/assets/sprites/8.png
flappy_bird_gymnasium/assets/sprites/9.png
flappy_bird_gymnasium/assets/sprites/background-day.png
flappy_bird_gymnasium/assets/sprites/background-night.png
flappy_bird_gymnasium/assets/sprites/base.png
flappy_bird_gymnasium/assets/sprites/bluebird-downflap.png
flappy_bird_gymnasium/assets/sprites/bluebird-midflap.png
flappy_bird_gymnasium/assets/sprites/bluebird-upflap.png
flappy_bird_gymnasium/assets/sprites/gameover.png
flappy_bird_gymnasium/assets/sprites/message.png
flappy_bird_gymnasium/assets/sprites/pipe-green.png
flappy_bird_gymnasium-0.4.0.dist-info/LICENSE
flappy_bird_gymnasium-0.4.0.dist-info/METADATA
flappy_bird_gymnasium-0.4.0.dist-info/WHEEL
flappy_bird_gymnasium-0.4.0.dist-info/entry_points.txt
flappy_bird_gymnasium-0.4.0.dist-info/top_level.txt
flappy_bird_gymnasium-0.4.0.dist-info/RECORD
